clipsnip/__init__.py
clipsnip/__main__.py
clipsnip/config.py
clipsnip/filename_parser.py
clipsnip/gif_extractor.py
clipsnip/media_searcher.py
clipsnip/quote.py
clipsnip/subtitle.py
tests/__init__.py
tests/candidates.py
tests/test_filename_parser.py
tests/test_media_searcher.py
clipsnip-0.0.20.dist-info/LICENSE
clipsnip-0.0.20.dist-info/METADATA
clipsnip-0.0.20.dist-info/WHEEL
clipsnip-0.0.20.dist-info/entry_points.txt
clipsnip-0.0.20.dist-info/top_level.txt
clipsnip-0.0.20.dist-info/RECORD
