Metadata-Version: 2.1
Name: clipsnip
Version: 0.0.20
Summary: Automated extraction of short clips from media files, using quotes.
Home-page: https://github.com/obroomhall/clipsnip
Author: Oliver Broomhall
Author-email: obroomhall@gmail.com
License: MIT
Keywords: ffmpeg trim subtitles gif gifv video media tv film movie clip
Platform: UNKNOWN
Classifier: Development Status :: 3 - Alpha
Classifier: Intended Audience :: Developers
Classifier: Intended Audience :: End Users/Desktop
Classifier: Topic :: Multimedia :: Video
Classifier: License :: OSI Approved :: MIT License
Classifier: Programming Language :: Python :: 3.5
Classifier: Programming Language :: Python :: 3.6
Classifier: Programming Language :: Python :: 3.7
Classifier: Programming Language :: Python :: 3.8
Classifier: Operating System :: OS Independent
Requires-Python: >=3.5, <4
Requires-Dist: pysubs2
Requires-Dist: python-opensubtitles
Requires-Dist: whoosh
Requires-Dist: tmdbsimple
Requires-Dist: scenedetect[opencv-headless]
Requires-Dist: ffsubsync
Requires-Dist: wheel
Requires-Dist: syllables
